transmutedb/__init__.py
transmutedb/cli/__init__.py
transmutedb/cli/doctor.py
transmutedb/cli/generate.py
transmutedb/cli/main.py
transmutedb/connectors/__init__.py
transmutedb/connectors/duck.py
transmutedb/connectors/rest.py
transmutedb/core/__init__.py
transmutedb/core/config.py
transmutedb/core/registry.py
transmutedb/transforms/__init__.py
transmutedb/transforms/polars_ops.py
transmutedb-0.1.1a1.dist-info/licenses/LICENSE.md
transmutedb-0.1.1a1.dist-info/licenses/LICENSE_ACKNOWLEDGEMENTS.md
transmutedb-0.1.1a1.dist-info/METADATA
transmutedb-0.1.1a1.dist-info/WHEEL
transmutedb-0.1.1a1.dist-info/entry_points.txt
transmutedb-0.1.1a1.dist-info/top_level.txt
transmutedb-0.1.1a1.dist-info/RECORD
