Metadata-Version: 2.4
Name: transmutedb
Version: 0.1.1a1
Summary: Parameter-driven data engineering framework (Kimball + SCD2) with CLI, Polars/DuckDB by default, Spark optional.
Author-email: Rawlsy-py <75848374+Rawlsy-py@users.noreply.github.com>
License: MIT License
Requires-Python: >=3.10
License-File: LICENSE.md
License-File: LICENSE_ACKNOWLEDGEMENTS.md
Requires-Dist: typer>=0.12
Requires-Dist: rich>=13
Requires-Dist: pydantic>=2
Requires-Dist: pluggy>=1.3
Requires-Dist: jinja2>=3.1
Requires-Dist: pyyaml>=6
Requires-Dist: tomli; python_version < "3.11"
Requires-Dist: polars>=1.4
Requires-Dist: duckdb>=1.0
Requires-Dist: httpx>=0.27
Provides-Extra: spark
Requires-Dist: pyspark>=3.4; extra == "spark"
Requires-Dist: delta-spark>=3.2.0; extra == "spark"
Provides-Extra: dev
Requires-Dist: pytest>=8; extra == "dev"
Requires-Dist: pytest-cov>=5; extra == "dev"
Requires-Dist: ruff>=0.5.6; extra == "dev"
Requires-Dist: mypy>=1.10; extra == "dev"
Dynamic: license-file
